2_Ripple_carry_adder/ripple_carry_adder_using_parameter.v
module ripple_carry_adder_using_parameter#(parameter N)(input [N-1:0]a,b, input cin, output [N-1:0]sum, output cout);
  
  wire [N:0]carr;
  assign cout = carr[N];
  assign carr[0] = cin;
  
  genvar i;
  generate
    for(i=0; i<N; i++)
      begin
        assign sum[i] = a[i]^b[i]^carr[i];
        assign carr[i+1] = (a[i]&b[i])|(b[i]&carr[i])|(carr[i]&a[i]);
      end
  endgenerate
endmodule

Ripple Carry Adder/ripple_carry_adder_using_parameter.sv
`timescale 1ns/1ps
//Hello, below is a testbench for the ripple carry adder module defined in ripple_carry_adder_using_parameter.sv
module ripple_carry_adder_tb;
  parameter N = 8;

  // DUT signals
  logic [N-1:0] a, b;
  logic         cin;
  logic [N-1:0] sum;
  logic         cout;

  // Instantiate DUT
  ripple_carry_adder_using_parameter #(.N(N)) dut (
    .a(a), .b(b), .cin(cin),
    .sum(sum), .cout(cout)
  );

  // Simulation block
  initial begin
    $dumpfile("ripple_carry_adder.vcd");
    $dumpvars(0, ripple_carry_adder_tb);

    $display("Time |       A |       B | CIN |     SUM | COUT | Expected SUM | Expected COUT");
    $display("--------------------------------------------------------------------------");

    // Loop through test cases
    for (int i = 0; i < 16; i++) begin
      a   = $urandom_range(0, 2**N - 1);
      b   = $urandom_range(0, 2**N - 1);
      cin = i % 2;
      #5;
      int expected_sum  = a + b + cin;
      bit expected_cout = (expected_sum >> N);
      expected_sum = expected_sum & ((1 << N) - 1);

      $display("%4t | %8b | %8b |  %0b  | %8b |  %0b  |    %8b    |       %0b",
               $time, a, b, cin, sum, cout, expected_sum, expected_cout);
    end

    $finish;
  end
endmodule

2_Ripple_carry_adder/ripple_carry_adder.vcd
$date
	Fri Nov 14 12:00:52 2025
$end
$version
	Icarus Verilog
$end
$timescale
	1ps
$end
$scope module ripple_carry_adder_tb $end
$var wire 8 ! sum [7:0] $end
$var wire 1 " cout $end
$var parameter 32 # N $end
$var reg 8 $ a [7:0] $end
$var reg 8 % b [7:0] $end
$var reg 1 & cin $end
$var reg 1 ' expected_cout $end
$var integer 32 ( expected_sum [31:0] $end
$var integer 32 ) i [31:0] $end
$scope module dut $end
$var wire 8 * a [7:0] $end
$var wire 8 + b [7:0] $end
$var wire 1 & cin $end
$var wire 8 , sum [7:0] $end
$var wire 1 " cout $end
$var wire 9 - carr [8:0] $end
$var parameter 32 . N $end
$scope begin genblk1[0] $end
$var parameter 2 / i $end
$upscope $end
$scope begin genblk1[1] $end
$var parameter 2 0 i $end
$upscope $end
$scope begin genblk1[2] $end
$var parameter 3 1 i $end
$upscope $end
$scope begin genblk1[3] $end
$var parameter 3 2 i $end
$upscope $end
$scope begin genblk1[4] $end
$var parameter 4 3 i $end
$upscope $end
$scope begin genblk1[5] $end
$var parameter 4 4 i $end
$upscope $end
$scope begin genblk1[6] $end
$var parameter 4 5 i $end
$upscope $end
$scope begin genblk1[7] $end
$var parameter 4 6 i $end
$upscope $end
$upscope $end
$upscope $end
$enddefinitions $end
$comment Show the parameter values. $end
$dumpall
b111 6
b110 5
b101 4
b100 3
b11 2
b10 1
b1 0
b0 /
b1000 .
b1000 #
$end
#0
$dumpvars
b0 -
b11010010 ,
b1000000 +
b10010010 *
b0 )
b0 (
0'
0&
b1000000 %
b10010010 $
0"
b11010010 !
$end
#5000
b110110 !
b110110 ,
b11 -
1&
b110001 %
b110001 +
b100 $
b100 *
b1 )
b11010010 (
#10000
1"
b1001100 !
b1001100 ,
b100001100 -
0&
b11000110 %
b11000110 +
b10000110 $
b10000110 *
b10 )
b110110 (
#15000
0"
b111100 !
b111100 ,
b111 -
1&
b1001 %
b1001 +
b110010 $
b110010 *
b11 )
1'
b1001100 (
#20000
1"
b110 !
b110 ,
b100000000 -
0&
b10000110 %
b10000110 +
b10000000 $
b10000000 *
b100 )
0'
b111100 (
#25000
b1011010 !
b1011010 ,
b101111111 -
1&
b10011110 %
b10011110 +
b10111011 $
b10111011 *
b101 )
1'
b110 (
#30000
b10111100 !
b10111100 ,
b110001100 -
0&
b11000110 %
b11000110 +
b11110110 $
b11110110 *
b110 )
b1011010 (
#35000
b1100000 !
b1100000 ,
b111111111 -
1&
b1100011 %
b1100011 +
b11111100 $
b11111100 *
b111 )
b10111100 (
#40000
0"
b10110111 !
b10110111 ,
b10000000 -
0&
b1010101 %
b1010101 +
b1100010 $
b1100010 *
b1000 )
b1100000 (
#45000
1"
b101110 !
b101110 ,
b111100111 -
1&
b111011 %
b111011 +
b11110010 $
b11110010 *
b1001 )
0'
b10110111 (
#50000
0"
b11010000 !
b11010000 ,
b11110 -
0&
b11000111 %
b11000111 +
b1001 $
b1001 *
b1010 )
1'
b101110 (
#55000
1"
b1100001 !
b1100001 ,
b111111111 -
1&
b1100111 %
b1100111 +
b11111001 $
b11111001 *
b1011 )
0'
b11010000 (
#60000
0"
b11010110 !
b11010110 ,
b11000000 -
0&
b1100010 %
b1100010 +
b1110100 $
b1110100 *
b1100 )
1'
b1100001 (
#65000
1"
b1101 !
b1101 ,
b111111101 -
1&
b1011110 %
b1011110 +
b10101110 $
b10101110 *
b1101 )
0'
b11010110 (
#70000
0"
b1001000 !
b1001000 ,
b1101100 -
0&
b110010 %
b110010 +
b10110 $
b10110 *
b1110 )
1'
b1101 (
#75000
b10110111 !
b10110111 ,
b11 -
1&
b10000101 %
b10000101 +
b110001 $
b110001 *
b1111 )
0'
b1001000 (
#80000
b10000 )
b10110111 (
